metron_talker/__init__.py
metron_talker/metron.py
metron_talker-0.2.3.dist-info/METADATA
metron_talker-0.2.3.dist-info/WHEEL
metron_talker-0.2.3.dist-info/entry_points.txt
metron_talker-0.2.3.dist-info/top_level.txt
metron_talker-0.2.3.dist-info/RECORD
