Metadata-Version: 2.4
Name: metron_talker
Version: 0.2.3
Summary: A Metron API talker for ComicTagger a cross-platform GUI/CLI app for writing metadata to comic archives
Home-page: https://github.com/comictagger/metron_talker
Author: ComicTagger team
Author-email: comictagger@gmail.com
License: Apache License 2.0
Keywords: comictagger,metron,metron.cloud,comics,comic,metadata,tagging,tagger
Classifier: Development Status :: 4 - Beta
Classifier: Environment :: Console
Classifier: Environment :: MacOS X
Classifier: Environment :: Plugins
Classifier: Environment :: Win32 (MS Windows)
Classifier: Environment :: X11 Applications :: Qt
Classifier: Intended Audience :: End Users/Desktop
Classifier: Natural Language :: English
Classifier: Operating System :: OS Independent
Classifier: Programming Language :: Python :: 3
Classifier: Programming Language :: Python :: 3 :: Only
Classifier: Topic :: Multimedia :: Graphics
Classifier: Topic :: Other/Nonlisted Topic
Classifier: Topic :: Utilities
Requires-Python: >=3.9
Provides-Extra: dev
Requires-Dist: black>=22; extra == "dev"
Requires-Dist: flake8==4.*; extra == "dev"
Requires-Dist: flake8-black; extra == "dev"
Requires-Dist: flake8-encodings; extra == "dev"
Requires-Dist: flake8-isort; extra == "dev"
Requires-Dist: invoke; extra == "dev"
Requires-Dist: isort>=5.10; extra == "dev"
Requires-Dist: pytest==7.*; extra == "dev"
Requires-Dist: setuptools>=42; extra == "dev"
Requires-Dist: setuptools-scm[toml]>=3.4; extra == "dev"
Requires-Dist: wheel; extra == "dev"
